pydmdll/__init__.py
pydmdll/damo.py
pydmdll/dm.dll
pydmdll-0.0.7.dist-info/LICENSE
pydmdll-0.0.7.dist-info/METADATA
pydmdll-0.0.7.dist-info/WHEEL
pydmdll-0.0.7.dist-info/top_level.txt
pydmdll-0.0.7.dist-info/RECORD
