Metadata-Version: 2.1
Name: pydmdll
Version: 0.0.7
Summary: 大漠插件dm.dll的Python接口
Home-page: https://github.com/Gaoyongxian666/pydmdll
Author: Gaoyongxian666
Author-email: g1695698547@163.com
License: UNKNOWN
Project-URL: Bug Reports, https://github.com/Gaoyongxian666/pydmdll
Project-URL: Source, https://github.com/Gaoyongxian666/pydmdll
Platform: UNKNOWN
Classifier: Programming Language :: Python :: 3
Classifier: License :: OSI Approved :: MIT License
Classifier: Operating System :: OS Independent
Requires-Dist: pywin32
